DataConnect/__init__.py
DataConnect/active_directory.py
DataConnect/database_connector.py
DataConnect/environment_setup.py
DataConnect-0.2.6.dist-info/LICENSE
DataConnect-0.2.6.dist-info/METADATA
DataConnect-0.2.6.dist-info/WHEEL
DataConnect-0.2.6.dist-info/top_level.txt
DataConnect-0.2.6.dist-info/RECORD
