Metadata-Version: 2.1
Name: DataConnect
Version: 0.2.6
Summary: This package contains connectors for databricks and sql server as well as setting up a flask environment project
Author: Ben Fuqua
Author-email: fuquac@slhs.org
Classifier: Programming Language :: Python :: 3
Classifier: License :: OSI Approved :: MIT License
Classifier: Operating System :: OS Independent
Requires-Python: >=3.9, <=3.10
License-File: LICENSE
Requires-Dist: numpy
Requires-Dist: Flask
Requires-Dist: SQLAlchemy
Requires-Dist: WTForms
Requires-Dist: flask-wtf
Requires-Dist: wtforms-sqlalchemy
Requires-Dist: flask-sqlalchemy
Requires-Dist: databricks-sql-connector[sqlalchemy]
Requires-Dist: pyodbc
Requires-Dist: ldap3
